LICENSE
poetry_chuy_plugin/__init__.py
poetry_chuy_plugin/plugin.py
poetry_chuy_plugin-0.2.1.dist-info/entry_points.txt
poetry_chuy_plugin-0.2.1.dist-info/LICENSE
poetry_chuy_plugin-0.2.1.dist-info/WHEEL
poetry_chuy_plugin-0.2.1.dist-info/METADATA
poetry_chuy_plugin-0.2.1.dist-info/RECORD
