Metadata-Version: 2.1
Name: poetry-chuy-plugin
Version: 0.2.1
Summary: Plugin to integrate Chuy with Poetry
Home-page: https://github.com/UltiRequiem/poetry-chuy-plugin
License: MIT
Keywords: commands,utilities,cli
Author: Eliaz Bobadilla
Author-email: eliaz.bobadilladev@gmail.com
Requires-Python: >=3.7,<4.0
Classifier: License :: OSI Approved :: MIT License
Classifier: Programming Language :: Python :: 3
Classifier: Programming Language :: Python :: 3.7
Classifier: Programming Language :: Python :: 3.8
Classifier: Programming Language :: Python :: 3.9
Requires-Dist: chuy (==1.2.0)
Requires-Dist: poetry (>=1.1.7,<2.0.0)
Project-URL: Repository, https://github.com/UltiRequiem/poetry-chuy-plugin
